{
  "Lay-Z-Spa Module Control": "Controllo Modulo Lay-Z-Spa",
  "SPA Control": "Controllo SPA",
  "Restart ESP": "Riavvia ESP",
  "Connected": "Connesso",
  "Connection Failed": "Connessione Fallita",
  "Connecting...": "Connessione...",
  "Hardware": "Hardware",
  "SPA Config": "Configurazione SPA",
  "Connectivity": "Connettività",
  "Files": "File",
  "Language:": "Lingua :",
  "English": "Inglese",
  "Français": "Francese",
  "Español": "Spagnolo",
  "Português": "Portoghese",
  "Italiano": "Italiano",
  "Deutsch": "Tedesco",
  
  "CURRENT STATUS": "STATO ATTUALE",
  "Virtual:": "Virtuale :",
  "Estimated temperature, calculated from pump and environment data.": "Temperatura stimata, calcolata dai dati della pompa e dell'ambiente.",
  "Physical Control Panel :": "Pannello di Controllo Fisico :",
  "Locked": "Bloccato",
  "Unlocked": "Sbloccato",
  "Target": "Obiettivo",
  "Ambient": "Ambiente",
  "Heating": "Riscaldamento",
  "Off": "Spento",
  "Heating Active": "Riscaldamento Attivo",
  "Standby": "Standby",
  "Pump": "Pompa",
  "Disable": "Disabilita",
  "Enable": "Abilita",
  "Units": "Unità",
  "Switch to °F": "Passa a °F",
  "Switch to °C": "Passa a °C",
  "Bubbles": "Bolle",
  "Hydrojets": "Idrogetti",
  "Display Brightness:": "Luminosità Display :",
  
  "Maintenance Schedule": "Programma di Manutenzione",
  "Chlorine:": "Cloro :",
  "Date:": "Data :",
  "Status:": "Stato :",
  "N/A": "N/D",
  "Reset": "Reset",
  "Filter Change:": "Cambio Filtro :",
  "Filter Rinse:": "Risciacquo Filtro :",
  "Filter Clean:": "Pulizia Filtro :",
  
  "Hardware Configuration": "Configurazione Hardware",
  "Select your CIO and DSP / PCB model :": "Seleziona il tuo modello CIO e DSP / PCB :",
  "Save": "Salva",
  "CIO Model (pump) :": "Modello CIO (pompa) :",
  "6-wire, pre-2021 (air)": "6 fili, pre-2021 (aria)",
  "6-wire, 2021 (air)": "6 fili, 2021 (aria)",
  "6-wire, 2021 (air+jet)": "6 fili, 2021 (aria+getto)",
  "6-wire, 54149E (air)": "6 fili, 54149E (aria)",
  "4-wire, 54173 (air+jet)": "4 fili, 54173 (aria+getto)",
  "4-wire, 54154 (air)": "4 fili, 54154 (aria)",
  "4-wire, 54144 (jet)": "4 fili, 54144 (getto)",
  "4-wire, 54138 (air+jet)": "4 fili, 54138 (aria+getto)",
  "4-wire, 54123 (air)": "4 fili, 54123 (aria)",
  "DSP Model (display) :": "Modello DSP (display) :",
  "Select your PCB :": "Seleziona il tuo PCB :",
  "V1": "V1",
  "V2": "V2",
  "V2B": "V2B",
  "Theoretically, any CIO can be combined with any DSP. Not tested, but cool if it works!": "Teoricamente, qualsiasi CIO può essere combinato con qualsiasi DSP. Non testato, ma sarebbe fantastico se funzionasse!",
  "Custom": "Personalizzato",
  "Same PCB as V2, but with wires moved to other pins for better compatibility with certain pumps": "Stesso PCB di V2, ma con i fili spostati su altri pin per una migliore compatibilità con alcune pompe",
  
  "Pin Assignment": "Assegnazione Pin",
  "Edit": "Modifica",
  "Cancel": "Annulla",
  "D0-D8 as marked on the ESP, but without the 'D'. The ESP will convert to GPIO numbers.": "D0-D8 come indicato sull'ESP, ma senza la 'D'. L'ESP convertirà in numeri GPIO.",
  "CIO": "CIO",
  "data/td/rx": "dati/td/rx",
  "clk/tx": "clk/tx",
  "cs/ld": "cs/ld",
  "DSP": "DSP",
  "data/td/tx": "dati/td/tx",
  "clk/rx": "clk/rx",
  "Audio": "Audio",
  
  "One Wire Ambient Temperature Sensor": "Sensore di Temperatura Ambiente One Wire",
  "Requires a DS18B20 sensor connected to the pin labeled 'Sensor Pin'. The sensor will periodically update the 'Ambient Temperature'.": "Richiede un sensore DS18B20 collegato al pin etichettato 'Sensor Pin'. Il sensore aggiornerà periodicamente la 'Temperatura Ambiente'.",
  "Sensor Pin (Dx)": "Pin Sensore (Dx)",
  "Sensor Status": "Stato Sensore",
  "Enabled": "Abilitato",
  "Disabled": "Disabilitato",
  "Enabled (Pin Modification)": "Abilitato (Modifica Pin)",
  
  "Power Levels (in Watts)": "Livelli di Potenza (in Watt)",
  "Customize power levels for different operating modes.": "Personalizza i livelli di potenza per le diverse modalità operative.",
  "Custom Power Levels Active": "Livelli di Potenza Personalizzati Attivi",
  "Default Power Levels": "Livelli di Potenza Predefiniti",
  "Heater 1": "Riscaldatore 1",
  "Heater 2": "Riscaldatore 2",
  "Idle": "Inattivo",
  "Air": "Aria",
  "Jets": "Getti",
  
  "Energy Costs": "Costi Energetici",
  "Configure energy price to calculate spa running costs.": "Configura il prezzo dell'energia per calcolare i costi di gestione della spa.",
  "Price per kWh (€):": "Prezzo per kWh (€) :",
  
  "Maintenance Intervals": "Intervalli di Manutenzione",
  "Define frequencies for spa maintenance tasks (e.g. chlorine, filter change, rinse, clean).": "Definisci le frequenze per le attività di manutenzione della spa (es. cloro, cambio filtro, risciacquo, pulizia).",
  "Chlorine (days):": "Cloro (giorni) :",
  "Filter Change (days):": "Cambio Filtro (giorni) :",
  "Filter Rinse (days):": "Risciacquo Filtro (giorni) :",
  "Filter Clean (days):": "Pulizia Filtro (giorni) :",
  
  "Audio and Notifications": "Audio e Notifiche",
  "Manage button sound activation and visual notification duration.": "Gestisci l'attivazione del suono dei pulsanti e la durata della notifica visiva.",
  "Enable Button Sounds": "Abilita Suoni Pulsanti",
  "Enable Notifications": "Abilita Notifiche",
  "Notification Duration (s):": "Durata Notifica (s) :",
  
  "Display Button Configuration": "Configurazione Pulsanti Display",
  "Allows you to physically disable spa control panel buttons you do not wish to use.": "Consente di disabilitare fisicamente i pulsanti del pannello di controllo della spa che non si desidera utilizzare.",
  "Enable Display Panel Buttons": "Abilita Pulsanti Pannello Display",
  "Power On/Off": "Accensione/Spegnimento",
  "Filter/Pump": "Filtro/Pompa",
  "Temp +": "Temp +",
  "Temp -": "Temp -",
  "Lock": "Blocca",
  "Unit": "Unità",
  "Timer": "Timer",
  "These icons represent the physical buttons on your spa control panel. The 'Enable Display Panel Buttons' option controls the overall responsiveness of the physical panel. Individual checkboxes control whether each physical button is interactive or disabled.": "Queste icone rappresentano i pulsanti fisici sul pannello di controllo della tua spa. L'opzione 'Abilita Pulsanti Pannello Display' controlla la reattività generale del pannello fisico. Le singole caselle di controllo gestiscono se ogni pulsante fisico è interattivo o disabilitato.",
  
  "Virtual Temperature Calibration": "Calibrazione Temperatura Virtuale",
  "If checked, virtual temperature is calibrated. To recalibrate, uncheck and save. Calibrate by keeping the heater OFF and the pump ON until the temperature has dropped a few degrees. Do not activate jets, bubbles, etc. during this time. Water temperature should differ by several degrees from ambient temperature at the beginning.": "Se selezionato, la temperatura virtuale è calibrata. Per ricalibrare, deseleziona e salva. Calibra mantenendo il riscaldatore SPENTO e la pompa ACCESA finché la temperatura non è scesa di qualche grado. Non attivare getti, bolle, ecc. durante questo periodo. La temperatura dell'acqua dovrebbe differire di diversi gradi dalla temperatura ambiente all'inizio.",
  "Calibrated": "Calibrato",
  
  "Scheduled Command Queue System": "Sistema Coda Comandi Programmati",
  "Schedule custom commands (e.g., activate bubbles, change temperature) to execute at specific times.": "Programma comandi personalizzati (es. attiva bolle, cambia temperatura) da eseguire in orari specifici.",
  "Command Queue Management": "Gestione Coda Comandi",
  "Command:": "Comando :",
  "Set target temp (20-40/68-104)": "Imposta temperatura target (20-40/68-104)",
  "Toggle units (°C/°F)": "Cambia unità (°C/°F)",
  "Toggle bubbles": "Attiva/disattiva bolle",
  "Toggle heater": "Attiva/disattiva riscaldatore",
  "Toggle pump": "Attiva/disattiva pompa",
  "Toggle lock": "Attiva/disattiva blocco",
  "Toggle hydrojets": "Attiva/disattiva idrogetti",
  "Set brightness (0-8)": "Imposta luminosità (0-8)",
  "Set beep (0/1 or 2+text=filename)": "Imposta beep (0/1 o 2+testo=nome file)",
  "Set ambient temp (°C)": "Imposta temp. ambiente (°C)",
  "Set ambient temp (°F)": "Imposta temp. ambiente (°F)",
  "Reset totals": "Reset totali",
  "Reset chlorine timer": "Reset timer cloro",
  "Reset filter replacement timer": "Reset timer sostituzione filtro",
  "Reset filter rinse timer": "Reset timer risciacquo filtro",
  "Reset filter clean timer": "Reset timer pulizia filtro",
  "Toggle Godmode": "Attiva/disattiva Godmode",
  "Set full power": "Imposta piena potenza",
  "Display text": "Visualizza testo",
  "Set ready": "Imposta pronto",
  "Set R": "Imposta R",
  "Set power on/off (0/1)": "Imposta accensione/spegnimento (0/1)",
  "Value:": "Valore :",
  "Enter value if applicable (0/1, temp, text...)": "Inserisci valore se applicabile (0/1, temp, testo...)",
  "Execution Time:": "Ora di Esecuzione :",
  "Repeat Interval (seconds):": "Intervallo di Ripetizione (secondi) :",
  "(0=once, 1h=3600, 1d=86400, 1w=604800)": "(0=una volta, 1h=3600, 1g=86400, 1s=604800)",
  "Add to Queue": "Aggiungi alla Coda",
  "Command queue is empty": "La coda dei comandi è vuota",
  "Clear Queue": "Svuota Coda",
  "Save to File": "Salva su File",
  "Load from File": "Carica da File",
  "Delete": "Elimina",
  "At:": "A :",
  "Immediately": "Immediatamente",
  "Repeat every {interval}s": "Ripeti ogni {interval}s",
  "Once": "Una volta",
  
  "Connectivity Configuration": "Configurazione Connettività",
  "Access Point": "Punto di Accesso",
  "Checked: ESP will connect using these credentials. Unchecked: ESP will use the last known credentials.": "Selezionato: l'ESP si connetterà utilizzando queste credenziali. Deselezionato: l'ESP utilizzerà le ultime credenziali conosciute.",
  "Enable Specific Access Point:": "Abilita Punto di Accesso Specifico :",
  "SSID :": "SSID :",
  "Password :": "Password :",
  "<enter password>": "<inserisci password>",
  "Show/Hide Password": "Mostra/Nascondi Password",
  "Hide Password": "Nascondi Password",
  "Show Password": "Mostra Password",
  
  "Soft Access Point": "Punto di Accesso Soft",
  "Enable ESP access point to be able to open this page before your network credentials are set. Normally, you would want this enabled! If your network is unavailable, the ESP will start its own access point.": "Abilita il punto di accesso ESP per poter aprire questa pagina prima che le credenziali di rete siano impostate. Normalmente, vorresti che questo fosse abilitato! Se la tua rete non è disponibile, l'ESP avvierà il proprio punto di accesso.",
  "Enable Soft AP (do not uncheck, you might lock yourself out!) :": "Abilita Soft AP (non deselezionare, potresti bloccarti l'accesso!) :",
  
  "Static IP": "IP Statico",
  "Allows setting a fixed IP address for the ESP instead of obtaining one via DHCP.": "Consente di impostare un indirizzo IP fisso per l'ESP invece di ottenerne uno tramite DHCP.",
  "Enable Static IP:": "Abilita IP Statico :",
  "IP Address :": "Indirizzo IP :",
  "Gateway IP Address :": "Indirizzo IP Gateway :",
  "Subnet Mask :": "Subnet Mask :",
  "DNS Server (Primary) :": "Server DNS (Primario) :",
  "DNS Server (Secondary) :": "Server DNS (Secondario) :",
  
  "NTP Server": "Server NTP",
  "Leave empty for default (pool.ntp.org) or set your preferred NTP server.": "Lascia vuoto per il valore predefinito (pool.ntp.org) o imposta il tuo server NTP preferito.",
  "Domain Name or IP Address :": "Nome di Dominio o Indirizzo IP :",
  
  "MQTT Configuration": "Configurazione MQTT",
  "Configure settings for MQTT connection.": "Configura le impostazioni per la connessione MQTT.",
  "Enable MQTT :": "Abilita MQTT :",
  "MQTT Host (IP or FQDN) :": "Host MQTT (IP o FQDN) :",
  "MQTT Port :": "Porta MQTT :",
  "MQTT Username :": "Nome Utente MQTT :",
  "MQTT Password :": "Password MQTT :",
  "MQTT Client ID :": "ID Client MQTT :",
  "MQTT Base Topic :": "Topic Base MQTT :",
  "MQTT Telemetry Interval (s) :": "Intervallo Telemetria MQTT (s) :",
  
  "Reset WiFi Configuration :": "Reset Configurazione WiFi :",
  "This button removes WiFi credentials. The ESP will restart and enable its own AP (if checked above). Connect to the WiFi AP with SSID 'layzspa_module######' and access http://192.168.4.2/wifi.html.": "Questo pulsante rimuove le credenziali WiFi. L'ESP si riavvierà e abiliterà il proprio AP (se selezionato sopra). Connettiti all'AP WiFi con SSID 'layzspa_module######' e accedi a http://192.168.4.2/wifi.html.",
  "Reset WiFi": "Reset WiFi",
  
  "File Management": "Gestione File",
  "Upload File": "Carica File",
  "Use this section to upload new files (firmware, configurations) to the ESP. Compressed files (.gz) are supported.": "Usa questa sezione per caricare nuovi file (firmware, configurazioni) sull'ESP. I file compressi (.gz) sono supportati.",
  "Select a file...": "Seleziona un file...",
  "No file selected": "Nessun file selezionato",
  "↑ Upload": "↑ Carica",
  "You can use compressed files (files with a .gz extension) to save space and bandwidth.": "Puoi usare file compressi (file con estensione .gz) per risparmiare spazio e larghezza di banda.",
  "Files on ESP Module": "File sul Modulo ESP",
  "List of files currently stored on the ESP. You can download or delete them.": "Elenco dei file attualmente memorizzati sull'ESP. Puoi scaricarli o eliminarli.",
  "File Name": "Nome File",
  "Size": "Dimensione",
  "Actions": "Azioni",
  "Loading files...": "Caricamento file...",
  "No files found.": "Nessun file trovato.",
  "Download": "Scarica",
  
  "© 2025 Lay-Z-Spa Control. All rights reserved.": "© 2025 - Lay-Z-Spa Module di visualapproach / UI di Dodemodexter",
  
  "Error": "Errore",
  "Success": "Successo",
  "Saving...": "Salvataggio...",
  "Uploading...": "Caricamento...",
  "Deleting...": "Eliminazione...",
  "OK": "OK",
  "Unknown": "Sconosciuto",
  "Loading": "Caricamento",
  
  "Invalid command:": "Comando non valido :",
  "Command \"{cmd}\" not sent: button or main display panel buttons are disabled by configuration.": "Comando \"{cmd}\" non inviato: i pulsanti del display o del pannello principale sono disabilitati dalla configurazione.",
  "Unauthorized Action": "Azione Non Autorizzata",
  "This action is disabled by the display buttons configuration. Please check the \"SPA Configuration\" tab.": "Questa azione è disabilitata dalla configurazione dei pulsanti del display. Si prega di controllare la scheda \"Configurazione SPA\".",
  "Maintenance timer reset is disabled by the display buttons configuration. Please check the \"SPA Configuration\" tab.": "Il reset del timer di manutenzione è disabilitato dalla configurazione dei pulsanti del display. Si prega di controllare la scheda \"Configurazione SPA\".",
  "Connection Error": "Errore di Connessione",
  "WebSocket is not connected. Please ensure the ESP is online and connected.": "WebSocket non è connesso. Assicurati che l'ESP sia online e connesso.",
  "WebSocket Error:": "Errore WebSocket :",
  "Reconnecting ({reconnectAttempts}/{MAX_RECONNECT_ATTEMPTS})...": "Riconnessione ({reconnectAttempts}/{MAX_RECONNECT_ATTEMPTS})...",
  "Restarting...": "Riavvio...",
  "The ESP is restarting. Connection may be temporarily lost. Please wait while we attempt to reconnect... Reconnecting ({reconnectAttempts}/{MAX_RECONNECT_ATTEMPTS})...": "L'ESP si sta riavviando. La connessione potrebbe essere temporaneamente persa. Attendi mentre tentiamo di riconnetterci... Riconnessione ({reconnectAttempts}/{MAX_RECONNECT_ATTEMPTS})...",
  "Connection Lost": "Connessione Persa",
  "Connection lost. Attempting to reconnect ({reconnectAttempts}/{MAX_RECONNECT_ATTEMPTS})...": "Connessione persa. Tentativo di riconnessione ({reconnectAttempts}/{MAX_RECONNECT_ATTEMPTS})...",
  "Disconnected": "Disconnesso",
  "Unable to reconnect to ESP after multiple attempts. Please check ESP power and your network.": "Impossibile riconnettersi all'ESP dopo diversi tentativi. Controlla l'alimentazione dell'ESP e la tua rete.",
  
  "Hardware configuration saved successfully! Restart the ESP to apply changes.": "Configurazione hardware salvata con successo! Riavvia l'ESP per applicare le modifiche.",
  "Failed to save hardware configuration. Status:": "Salvataggio configurazione hardware fallito. Stato :",
  "Failed to save hardware configuration. Please try again.": "Salvataggio configurazione hardware fallito. Riprova.",
  "Network Error": "Errore di Rete",
  "Unable to communicate with device.": "Impossibile comunicare con il dispositivo.",
  
  "Configuration saved successfully! Restart the ESP to apply changes.": "Configurazione salvata con successo! Riavvia l'ESP per applicare le modifiche.",
  "Failed to save configuration. Please try again.": "Salvataggio configurazione fallito. Riprova.",
  
  "Are you sure you want to restart the ESP? This will temporarily disconnect the spa.": "Sei sicuro di voler riavviare l'ESP? Questo disconnetterà temporaneamente la spa.",
  "Failed to send restart command. Status: {status}.": "Invio comando di riavvio fallito. Stato: {status}.",
  "Restart Error": "Errore di Riavvio",
  
  "The value for this command must be a number.": "Il valore per questo comando deve essere un numero.",
  "Text for \"Display text\" command cannot be empty.": "Il testo per il comando \"Visualizza testo\" non può essere vuoto.",
  "Please enter a valid execution time.": "Inserisci un'ora di esecuzione valida.",
  "Please select a command.": "Seleziona un comando.",
  
  "Delete Command": "Elimina Comando",
  "Are you sure you want to delete this scheduled command?": "Sei sicuro di voler eliminare questo comando programmato?",
  
  "Clear Command Queue": "Svuota Coda Comandi",
  "Are you sure you want to clear the scheduled command queue? This action is irreversible.": "Sei sicuro di voler svuotare la coda dei comandi programmati? Questa azione è irreversibile.",
  
  "Save Command Queue": "Salva Coda Comandi",
  "Enter a file name to save the current command queue to the ESP - WARNING no spaces or special characters (e.g., Daily_Heat) :": "Inserisci un nome file per salvare la coda dei comandi attuale sull'ESP - ATTENZIONE senza spazi o caratteri speciali (es. Daily_Heat) :",
  "File name cannot be empty.": "Il nome del file non può essere vuoto.",
  "File name should not contain spaces or special characters. Use hyphens or underscores if needed.": "Il nome del file non deve contenere spazi o caratteri speciali. Usa trattini o underscore se necessario.",
  "Daily_Heat": "Calore_Quotidiano",
  "Command queue save request sent for \"{filename}\". The ESP will now save its current queue.": "Richiesta di salvataggio della coda comandi inviata per \"{filename}\". L'ESP ora salverà la sua coda attuale.",
  "Failed to send command queue save request. Status: {status}": "Invio richiesta di salvataggio della coda comandi fallito. Stato: {status}",
  
  "Load Command Queue": "Carica Coda Comandi",
  "Select a command file to load from the ESP, or enter a file name below :": "Seleziona un file di comando da caricare dall'ESP, o inserisci un nome file qui sotto :",
  "Enter the file name to load from the ESP (e.g., mycommands_schedule.json) :": "Inserisci il nome del file da caricare dall'ESP (es. mycommands_schedule.json) :",
  "Daily_Heat_schedule.json": "Calore_Quotidiano_schedule.json",
  "Command queue load request sent for \"{filename}\". The ESP will now load and apply it.": "Richiesta di caricamento della coda comandi inviata per \"{filename}\". L'ESP ora la caricherà e la applicherà.",
  "Failed to send command queue load request. Status: {status}": "Invio richiesta di caricamento della coda comandi fallito. Stato: {status}",
  
  "WiFi Reset": "Reset WiFi",
  "ESP is restarting now. Please connect to the \"layzspa_module######\" access point and reconfigure your WiFi via http://192.168.4.2/wifi.html.": "L'ESP si sta riavviando. Si prega di connettersi al punto di accesso \"layzspa_module######\" e riconfigurare il WiFi tramite http://192.168.4.2/wifi.html.",
  "Reset Error": "Errore Reset",
  "Failed to reset WiFi. Status: {status}.": "Reset WiFi fallito. Stato: {status}.",
  
  "Upload Complete": "Caricamento Completato",
  "\"{filename}\" uploaded successfully!": "\"{filename}\" caricato con successo!",
  "\"{filename}\" upload completed (may have succeeded).": "Caricamento di \"{filename}\" completato (potrebbe essere riuscito).",
  "Please select a file to upload.": "Seleziona un file da caricare.",
  
  "Download File": "Scarica File",
  "Do you want to download \"{filename}\"?": "Vuoi scaricare \"{filename}\"?",
  
  "Delete File": "Elimina File",
  "Are you sure you want to delete \"{filename}\"? This action is irreversible.": "Sei sicuro di voler eliminare \"{filename}\"? Questa azione è irreversibile.",
  "Deletion Success": "Eliminazione Riuscita",
  "\"{filename}\" deleted successfully!": "\"{filename}\" eliminato con successo!",
  "Deletion Error": "Errore Eliminazione",
  "Failed to delete \"{filename}\". Status: {status}. Response: {errorText}": "Eliminazione di \"{filename}\" fallita. Stato: {status}. Risposta: {errorText}",
  "Unable to communicate with ESP during deletion: {error.message}": "Impossibile comunicare con l'ESP durante l'eliminazione: {error.message}",
  
  "Reset Totals": "Reset Totali",
  "Are you sure you want to reset all runtime and cost totals? This action is irreversible.": "Sei sicuro di voler resettare tutti i totali di tempo di esecuzione e costo? Questa azione è irreversibile.",
  "Totals have been reset.": "I totali sono stati resettati.",
  
  "Reset {timerName}": "Reset {timerName}",
  "Are you sure you want to reset the timer for \"{timerName}\"?": "Sei sicuro di voler resettare il timer per \"{timerName}\"?",
  "The timer for \"{timerName}\" has been reset.": "Il timer per \"{timerName}\" è stato resettato.",
  "Maintenance elements for {prefix} not found.": "Elementi di manutenzione per {prefix} non trovati.",
  
  "OVERDUE": "IN RITARDO",
  "1 Day remaining": "1 Giorno rimanente",
  "{daysLeft} Days remaining": "{daysLeft} Giorni rimanenti",
  
  "Please \"Enable Display Panel Buttons\" first to modify individual settings.": "Abilita prima i \"Pulsanti Pannello Display\" per modificare le impostazioni individuali.",
  
  "Unknown Command": "Comando Sconosciuto",
  "HTTP Error! Status: {status}": "Errore HTTP! Stato: {status}",
  "Load Error": "Errore di Caricamento",
  "Unable to list files from ESP: {error.message}. Ensure /dir/ path is accessible.": "Impossibile elencare i file dall'ESP: {error.message}. Assicurarsi che il percorso /dir/ sia accessibile.",
  "Error loading files: {error.message}": "Errore durante il caricamento dei file: {error.message}",
  "Error displaying files:": "Errore durante la visualizzazione dei file:",
  
  "Uploading \"{filename}\"...": "Caricamento di \"{filename}\"...",
  "Deleting \"{filename}\"...": "Eliminazione di \"{filename}\"...",
  
  "HTTP {status}": "HTTP {status}",
  "Error fetching directory listing:": "Errore durante il recupero dell'elenco delle directory:",
  
  "Saved &check;": "Salvato &check;",
  "Failed to save SPA config. Status:": "Salvataggio configurazione SPA fallito. Stato:",
  "Save Failed!": "Salvataggio Fallito!",
  "Failed (Network Error)": "Fallito (Errore di Rete)",
  
  "Enter file name": "Inserisci nome file",
  "Restart ESP Configuration": "Configurazione Riavvio ESP",
  "Reset WiFi Configuration": "Reset Configurazione WiFi",
  "Are you sure you want to reset WiFi? This will remove credentials and the ESP will restart, enabling its own access point.": "Sei sicuro di voler resettare il WiFi? Questo rimuoverà le credenziali e l'ESP si riavvierà, abilitando il proprio punto di accesso.",
  
  "JSON parse error for received message:": "Errore di parsing JSON per il messaggio ricevuto :",
  "JSON parse error for command queue from HTTP:": "Errore di parsing JSON per la coda comandi da HTTP :",
  "Failed to load command queue via HTTP. Status:": "Caricamento coda comandi via HTTP fallito. Stato :",
  "XMLHttpRequest error for /getcommands/. This often occurs when loading HTML directly from your file system (file://) due to browser security restrictions (Same-Origin Policy). To fix, serve your HTML using a local web server (e.g., Python's `python -m http.server`) and access it via `http://localhost:PORT/yourfile.html`.": "Errore XMLHttpRequest per /getcommands/. Questo si verifica spesso quando si carica HTML direttamente dal file system (file://) a causa delle restrizioni di sicurezza del browser (Same-Origin Policy). Per risolvere, servi il tuo HTML usando un server web locale (es. `python -m http.server` di Python) e accedivi tramite `http://localhost:PORT/tuofile.html`.",
  "Received COMMAND_QUEUE data in unexpected format:": "Dati COMMAND_QUEUE ricevuti in formato inatteso :",
  
  "JSON parse error for hardware config:": "Errore di parsing JSON per la configurazione hardware :",
  "Failed to load hardware config. Status:": "Caricamento configurazione hardware fallito. Stato :",
  "XMLHttpRequest error for /gethardware/. This often occurs when loading HTML directly from your file system (file://) due to browser security restrictions (Same-Origin Policy). To fix, serve your HTML using a local web server (e.g., Python's `python -m http.server`) and access it via `http://localhost:PORT/yourfile.html`.": "Errore XMLHttpRequest per /gethardware/. Questo si verifica spesso quando si carica HTML direttamente dal file system (file://) a causa delle restrizioni di sicurezza del browser (Same-Origin Policy). Per risolvere, servi il tuo HTML usando un server web locale (es. `python -m http.server` di Python) e accedivi tramite `http://localhost:PORT/tuofile.html`.",
  
  "JSON parse error for SPA configuration from /getconfig/:": "Errore di parsing JSON per la configurazione SPA da /getconfig/ :",
  "Failed to load SPA configuration from /getconfig/. Status:": "Caricamento configurazione SPA da /getconfig/ fallito. Stato :",
  "XMLHttpRequest error for /getconfig/. Using existing SPA configuration data. Ensure ESP endpoint is accessible.": "Errore XMLHttpRequest per /getconfig/. Utilizzo dei dati di configurazione SPA esistenti. Assicurati che l'endpoint ESP sia accessibile.",
  
  "XMLHttpRequest error during saveHardwareConfig. Check network/ESP response.": "Errore XMLHttpRequest durante saveHardwareConfig. Controlla la risposta di rete/ESP.",
  "XMLHttpRequest error during saveSpaConfig. Check network/ESP response.": "Errore XMLHttpRequest durante saveSpaConfig. Controlla la risposta di rete/ESP.",
  
  "Failed to send add command. Status:": "Invio comando di aggiunta fallito. Stato :",
  "Failed to add command. Status: {status}": "Aggiunta comando fallita. Stato: {status}",
  "XMLHttpRequest error while adding command. Check network/ESP response.": "Errore XMLHttpRequest durante l'aggiunta del comando. Controlla la risposta di rete/ESP.",
  
  "Failed to delete command. Status:": "Eliminazione comando fallita. Stato :",
  "Failed to delete command. Status: {status}": "Eliminazione comando fallita. Stato: {status}",
  "XMLHttpRequest error while deleting command. Check network/ESP response.": "Errore XMLHttpRequest durante l'eliminazione del comando. Controlla la risposta di rete/ESP.",
  
  "Failed to send clear queue command. Status:": "Invio comando svuota coda fallito. Stato :",
  "Failed to clear command queue. Status: {status}": "Svuotamento coda comandi fallito. Stato: {status}",
  "XMLHttpRequest error while clearing command queue. Check network/ESP response.": "Errore XMLHttpRequest durante lo svuotamento della coda comandi. Controlla la risposta di rete/ESP.",
  
  "JSON parse error for network configuration (WiFi):": "Errore di parsing JSON per la configurazione di rete (WiFi) :",
  "Failed to load network configuration (WiFi). Status:": "Caricamento configurazione di rete (WiFi) fallito. Stato :",
  "XMLHttpRequest error for /getwifi/. Ensure ESP endpoint is accessible.": "Errore XMLHttpRequest per /getwifi/. Assicurati che l'endpoint ESP sia accessibile.",
  
  "JSON parse error for MQTT configuration:": "Errore di parsing JSON per la configurazione MQTT :",
  "Failed to load MQTT configuration. Status:": "Caricamento configurazione MQTT fallito. Stato :",
  "XMLHttpRequest error for /getmqtt/. Ensure ESP endpoint is accessible.": "Errore XMLHttpRequest per /getmqtt/. Assicurati che l'endpoint ESP sia accessibile.",
  
  "Error during combined connectivity configuration loading:": "Errore durante il caricamento combinato della configurazione di connettività :",
  "Failed to save configuration {sectionId}. Status:": "Salvataggio configurazione {sectionId} fallito. Stato :",
  "XMLHttpRequest error while saving {sectionId}. Check network/ESP response.": "Errore XMLHttpRequest durante il salvataggio di {sectionId}. Controlla la risposta di rete/ESP.",
  
  "SPA Configuration": "Configurazione SPA",
  "Configure settings for spa maintenance tasks": "Configura le impostazioni per le attività di manutenzione della spa"
}
